pyintel471/__init__.py
pyintel471/api.py
pyintel471-0.1.1.dist-info/LICENSE
pyintel471-0.1.1.dist-info/METADATA
pyintel471-0.1.1.dist-info/WHEEL
pyintel471-0.1.1.dist-info/top_level.txt
pyintel471-0.1.1.dist-info/RECORD
